{
    "event": null,
    "data": [
        {
            "riders": [
                {
                    "team_rank": 0,
                    "rider_rank": 5,
                    "rider_name": "Gavin Moore",
                    "rider_position": null,
                    "team_name": "Race3R",
                    "wkg": 4.2,
                    "power": 251,
                    "completed_laps": 1,
                    "total_time": 3429.675,
                    "time_gap": 0.422,
                    "avg_speed": 39.362,
                    "distance": 139012
                },
                {
                    "team_rank": 0,
                    "rider_rank": 2,
                    "rider_name": "Kristian Kroll",
                    "rider_position": null,
                    "team_name": "Race3R",
                    "wkg": 3.8,
                    "power": 279,
                    "completed_laps": 1,
                    "total_time": 3429.418,
                    "time_gap": 0.165,
                    "avg_speed": 39.365,
                    "distance": 210667
                },
                {
                    "team_rank": 0,
                    "rider_rank": 6,
                    "rider_name": "Kristin Moat (Race3R Take That)",
                    "rider_position": null,
                    "team_name": "Race3R",
                    "wkg": 3.6,
                    "power": 250,
                    "completed_laps": 1,
                    "total_time": 3429.825,
                    "time_gap": 0.572,
                    "avg_speed": 39.361,
                    "distance": 415493
                },
                {
                    "team_rank": 0,
                    "rider_rank": 1,
                    "rider_name": "Unai Balenciaga",
                    "rider_position": null,
                    "team_name": "Race3R",
                    "wkg": 4.3,
                    "power": 280,
                    "completed_laps": 1,
                    "total_time": 3429.253,
                    "time_gap": 0,
                    "avg_speed": 39.367,
                    "distance": 462143
                },
                {
                    "team_rank": 0,
                    "rider_rank": 3,
                    "rider_name": "James Orton",
                    "rider_position": null,
                    "team_name": "Race3R",
                    "wkg": 3.2,
                    "power": 241,
                    "completed_laps": 1,
                    "total_time": 3429.627,
                    "time_gap": 0.374,
                    "avg_speed": 39.363,
                    "distance": 707206
                },
                {
                    "team_rank": 1,
                    "rider_rank": 4,
                    "rider_name": "Stephen Carson (R3R Take That)",
                    "rider_position": null,
                    "team_name": "Race3R",
                    "wkg": 3.9,
                    "power": 247,
                    "completed_laps": 1,
                    "total_time": 3429.645,
                    "time_gap": 0.392,
                    "avg_speed": 39.363,
                    "distance": 745686
                }
            ],
            "rank": 4,
            "total_distance": 281.596,
            "total_power": 3429.645,
            "zone": 2,
            "dropped_riders": 1,
            "coffee_class": "Frappe",
            "team_time": 3429.645,
            "lap_count": 1,
            "avg_speed": 39.36,
            "total_tss": 0,
            "total_if": 0,
            "total_np": 0,
            "team_name": "R3R Playboys",
            "rider_count": 6,
            "completed": 0,
            "total_time_calc": 3429.645
        },
        {
            "riders": [
                {
                    "team_rank": 0,
                    "rider_rank": 2,
                    "rider_name": "Catherine Allen",
                    "rider_position": null,
                    "team_name": "Race3R",
                    "wkg": 2.6,
                    "power": 137,
                    "completed_laps": 1,
                    "total_time": 4272.141,
                    "time_gap": 0.019,
                    "avg_speed": 31.6,
                    "distance": 281872
                },
                {
                    "team_rank": 0,
                    "rider_rank": 4,
                    "rider_name": "Debs Stockley (R3R Bucks Fizz)",
                    "rider_position": null,
                    "team_name": "Race3R",
                    "wkg": 2.5,
                    "power": 141,
                    "completed_laps": 1,
                    "total_time": 4273.836,
                    "time_gap": 1.714,
                    "avg_speed": 31.588,
                    "distance": 320052
                },
                {
                    "team_rank": 1,
                    "rider_rank": 3,
                    "rider_name": "Hazel Ley (Race3R Bananarama)",
                    "rider_position": null,
                    "team_name": "Race3R",
                    "wkg": 2.3,
                    "power": 141,
                    "completed_laps": 1,
                    "total_time": 4273.829,
                    "time_gap": 1.707,
                    "avg_speed": 31.588,
                    "distance": 414829
                },
                {
                    "team_rank": 0,
                    "rider_rank": 1,
                    "rider_name": "Michele Bennett (R3R Take That)",
                    "rider_position": null,
                    "team_name": "Race3R",
                    "wkg": 2.4,
                    "power": 151,
                    "completed_laps": 1,
                    "total_time": 4272.122,
                    "time_gap": 0,
                    "avg_speed": 31.6,
                    "distance": 506231
                }
            ],
            "rank": 18,
            "total_distance": 1125.78,
            "total_power": 4273.829,
            "zone": 2,
            "dropped_riders": 1,
            "coffee_class": "Vienna",
            "team_time": 4273.829,
            "lap_count": 1,
            "avg_speed": 31.59,
            "total_tss": 0,
            "total_if": 0,
            "total_np": 0,
            "team_name": "R3R Lunachicks",
            "rider_count": 4,
            "completed": 0,
            "total_time_calc": 4273.829
        },
        {
            "riders": [
                {
                    "team_rank": 0,
                    "rider_rank": 6,
                    "rider_name": "Paul Wakefield (Herd of Lions)",
                    "rider_position": null,
                    "team_name": "HERD",
                    "wkg": 3.3,
                    "power": 224,
                    "completed_laps": 1,
                    "total_time": 3529.988,
                    "time_gap": 2.381,
                    "avg_speed": 38.244,
                    "distance": 38218
                },
                {
                    "team_rank": 0,
                    "rider_rank": 5,
                    "rider_name": "M Hepples (Herd of Lions)",
                    "rider_position": null,
                    "team_name": "HERD",
                    "wkg": 3.3,
                    "power": 219,
                    "completed_laps": 1,
                    "total_time": 3529.654,
                    "time_gap": 2.047,
                    "avg_speed": 38.247,
                    "distance": 146618
                },
                {
                    "team_rank": 0,
                    "rider_rank": 2,
                    "rider_name": "Treve Eddy (Herd of Tigers)",
                    "rider_position": null,
                    "team_name": "HERD",
                    "wkg": 2.9,
                    "power": 214,
                    "completed_laps": 1,
                    "total_time": 3528.02,
                    "time_gap": 0.413,
                    "avg_speed": 38.265,
                    "distance": 875990
                },
                {
                    "team_rank": 0,
                    "rider_rank": 1,
                    "rider_name": "Jake Sanderson (Herd of Lions)",
                    "rider_position": null,
                    "team_name": "HERD",
                    "wkg": 3.6,
                    "power": 213,
                    "completed_laps": 1,
                    "total_time": 3527.607,
                    "time_gap": 0,
                    "avg_speed": 38.27,
                    "distance": 894382
                },
                {
                    "team_rank": 0,
                    "rider_rank": 3,
                    "rider_name": "Simon Gregory (Herd of Lions)",
                    "rider_position": null,
                    "team_name": "HERD",
                    "wkg": 3.2,
                    "power": 247,
                    "completed_laps": 1,
                    "total_time": 3528.809,
                    "time_gap": 1.202,
                    "avg_speed": 38.257,
                    "distance": 939457
                },
                {
                    "team_rank": 1,
                    "rider_rank": 4,
                    "rider_name": "Hans Mallegrom (Herd of Lions)",
                    "rider_position": null,
                    "team_name": "HERD",
                    "wkg": 3.2,
                    "power": 231,
                    "completed_laps": 1,
                    "total_time": 3529.034,
                    "time_gap": 1.427,
                    "avg_speed": 38.254,
                    "distance": 1076222
                }
            ],
            "rank": 5,
            "total_distance": 380.985,
            "total_power": 3529.034,
            "zone": 2,
            "dropped_riders": 1,
            "coffee_class": "Frappe",
            "team_time": 3529.034,
            "lap_count": 1,
            "avg_speed": 38.25,
            "total_tss": 449,
            "total_if": 929,
            "total_np": 1387,
            "team_name": "HERD of Lions",
            "rider_count": 6,
            "completed": 0,
            "total_time_calc": 3529.034
        },
        {
            "riders": [
                {
                    "team_rank": 1,
                    "rider_rank": 3,
                    "rider_name": "F.ossy No Legs (Herd)",
                    "rider_position": null,
                    "team_name": "HERD",
                    "wkg": 2.1,
                    "power": 175,
                    "completed_laps": 1,
                    "total_time": 4445.75,
                    "time_gap": 0.132,
                    "avg_speed": 30.366,
                    "distance": 326458
                },
                {
                    "team_rank": 0,
                    "rider_rank": 1,
                    "rider_name": "Dave Roberts (Herd Tigers)",
                    "rider_position": null,
                    "team_name": "HERD",
                    "wkg": 2.2,
                    "power": 173,
                    "completed_laps": 1,
                    "total_time": 4445.618,
                    "time_gap": 0,
                    "avg_speed": 30.367,
                    "distance": 482656
                },
                {
                    "team_rank": 0,
                    "rider_rank": 4,
                    "rider_name": "Gordon Sloan (Herd of Buffalo)",
                    "rider_position": null,
                    "team_name": "HERD",
                    "wkg": 2.1,
                    "power": 173,
                    "completed_laps": 1,
                    "total_time": 4446.581,
                    "time_gap": 0.963,
                    "avg_speed": 30.36,
                    "distance": 613280
                },
                {
                    "team_rank": 0,
                    "rider_rank": 2,
                    "rider_name": "Paul Fabi (Herd of Honey Badgers)",
                    "rider_position": null,
                    "team_name": "HERD",
                    "wkg": 2,
                    "power": 184,
                    "completed_laps": 1,
                    "total_time": 4445.735,
                    "time_gap": 0.117,
                    "avg_speed": 30.366,
                    "distance": 694288
                }
            ],
            "rank": 19,
            "total_distance": 1297.701,
            "total_power": 4445.75,
            "zone": 2,
            "dropped_riders": 1,
            "coffee_class": "Mocha",
            "team_time": 4445.75,
            "lap_count": 1,
            "avg_speed": 30.37,
            "total_tss": 0,
            "total_if": 0,
            "total_np": 0,
            "team_name": "HERD of Honey Badgers",
            "rider_count": 4,
            "completed": 0,
            "total_time_calc": 4445.75
        },
        {
            "riders": [
                {
                    "team_rank": 0,
                    "rider_rank": 1,
                    "rider_name": "Brian Rhoden ( WKG VOMIT )",
                    "rider_position": null,
                    "team_name": "teamWKG",
                    "wkg": 3.8,
                    "power": 207,
                    "completed_laps": 1,
                    "total_time": 3713.984,
                    "time_gap": 0,
                    "avg_speed": 36.349,
                    "distance": 53663
                },
                {
                    "team_rank": 1,
                    "rider_rank": 3,
                    "rider_name": "Duncan Bruce",
                    "rider_position": null,
                    "team_name": "teamWKG",
                    "wkg": 3.4,
                    "power": 270,
                    "completed_laps": 1,
                    "total_time": 3719.29,
                    "time_gap": 5.306,
                    "avg_speed": 36.297,
                    "distance": 250081
                },
                {
                    "team_rank": 0,
                    "rider_rank": 2,
                    "rider_name": "Stefan Granqvist (WKG VOMIT)",
                    "rider_position": null,
                    "team_name": "teamWKG",
                    "wkg": 3.4,
                    "power": 274,
                    "completed_laps": 1,
                    "total_time": 3716.5,
                    "time_gap": 2.516,
                    "avg_speed": 36.324,
                    "distance": 898700
                }
            ],
            "rank": 12,
            "total_distance": 571.241,
            "total_power": 3719.29,
            "zone": 2,
            "dropped_riders": 1,
            "coffee_class": "Frappe",
            "team_time": 3719.29,
            "lap_count": 1,
            "avg_speed": 36.3,
            "total_tss": 0,
            "total_if": 0,
            "total_np": 0,
            "team_name": "WKG VOMIT ",
            "rider_count": 3,
            "completed": 0,
            "total_time_calc": 3719.29
        },
        {
            "riders": [
                {
                    "team_rank": 0,
                    "rider_rank": 3,
                    "rider_name": "KeithD (WKG FUN)",
                    "rider_position": null,
                    "team_name": "teamWKG",
                    "wkg": 2.9,
                    "power": 229,
                    "completed_laps": 1,
                    "total_time": 3959.196,
                    "time_gap": 0.097,
                    "avg_speed": 34.098,
                    "distance": 13747
                },
                {
                    "team_rank": 0,
                    "rider_rank": 6,
                    "rider_name": "Maria Trilk (WKG FUN)",
                    "rider_position": null,
                    "team_name": "teamWKG",
                    "wkg": 2.4,
                    "power": 139,
                    "completed_laps": 1,
                    "total_time": 4180.302,
                    "time_gap": 221.203,
                    "avg_speed": 32.294,
                    "distance": 27994
                },
                {
                    "team_rank": 1,
                    "rider_rank": 4,
                    "rider_name": "KatherineD (WKG FUN)",
                    "rider_position": null,
                    "team_name": "teamWKG",
                    "wkg": 2.9,
                    "power": 174,
                    "completed_laps": 1,
                    "total_time": 3959.294,
                    "time_gap": 0.195,
                    "avg_speed": 34.097,
                    "distance": 51644
                },
                {
                    "team_rank": 0,
                    "rider_rank": 2,
                    "rider_name": "Percy S (WKG FUN)",
                    "rider_position": null,
                    "team_name": "teamWKG",
                    "wkg": 2.9,
                    "power": 168,
                    "completed_laps": 1,
                    "total_time": 3959.152,
                    "time_gap": 0.053,
                    "avg_speed": 34.098,
                    "distance": 166608
                },
                {
                    "team_rank": 0,
                    "rider_rank": 1,
                    "rider_name": "Stuart Woodsell",
                    "rider_position": null,
                    "team_name": "teamWKG",
                    "wkg": 2.8,
                    "power": 237,
                    "completed_laps": 1,
                    "total_time": 3959.099,
                    "time_gap": 0,
                    "avg_speed": 34.099,
                    "distance": 211126
                },
                {
                    "team_rank": 0,
                    "rider_rank": 5,
                    "rider_name": "Andrew lawrence WKG FUN",
                    "rider_position": null,
                    "team_name": "",
                    "wkg": 2.8,
                    "power": 237,
                    "completed_laps": 1,
                    "total_time": 3959.383,
                    "time_gap": 0.284,
                    "avg_speed": 34.096,
                    "distance": 1034876
                }
            ],
            "rank": 15,
            "total_distance": 811.245,
            "total_power": 3959.294,
            "zone": 2,
            "dropped_riders": 1,
            "coffee_class": "Latte",
            "team_time": 3959.294,
            "lap_count": 1,
            "avg_speed": 34.1,
            "total_tss": 575,
            "total_if": 1193,
            "total_np": 1748,
            "team_name": "WKG FUN ",
            "rider_count": 6,
            "completed": 0,
            "total_time_calc": 3959.294
        },
        {
            "riders": [
                {
                    "team_rank": 0,
                    "rider_rank": 2,
                    "rider_name": "Dave Crook",
                    "rider_position": null,
                    "team_name": "teamWKG",
                    "wkg": 2.9,
                    "power": 252,
                    "completed_laps": 1,
                    "total_time": 3673.724,
                    "time_gap": 0.049,
                    "avg_speed": 36.747,
                    "distance": 20998
                },
                {
                    "team_rank": 1,
                    "rider_rank": 4,
                    "rider_name": "Paul Trilk (WKG GH)",
                    "rider_position": null,
                    "team_name": "teamWKG",
                    "wkg": 2.7,
                    "power": 214,
                    "completed_laps": 1,
                    "total_time": 3674.031,
                    "time_gap": 0.356,
                    "avg_speed": 36.744,
                    "distance": 27966
                },
                {
                    "team_rank": 0,
                    "rider_rank": 1,
                    "rider_name": "Kevin Wiltshire (WKG GH)",
                    "rider_position": null,
                    "team_name": "teamWKG",
                    "wkg": 3,
                    "power": 266,
                    "completed_laps": 1,
                    "total_time": 3673.675,
                    "time_gap": 0,
                    "avg_speed": 36.748,
                    "distance": 392756
                },
                {
                    "team_rank": 0,
                    "rider_rank": 3,
                    "rider_name": "Hal Wye (WKG GH)",
                    "rider_position": null,
                    "team_name": "teamWKG",
                    "wkg": 3.1,
                    "power": 200,
                    "completed_laps": 1,
                    "total_time": 3673.912,
                    "time_gap": 0.237,
                    "avg_speed": 36.746,
                    "distance": 406022
                },
                {
                    "team_rank": 0,
                    "rider_rank": 5,
                    "rider_name": "Mike Pickering (WKG GH)",
                    "rider_position": null,
                    "team_name": "teamWKG",
                    "wkg": 2.6,
                    "power": 198,
                    "completed_laps": 1,
                    "total_time": 3681.154,
                    "time_gap": 7.479,
                    "avg_speed": 36.673,
                    "distance": 911154
                }
            ],
            "rank": 11,
            "total_distance": 525.982,
            "total_power": 3674.031,
            "zone": 2,
            "dropped_riders": 1,
            "coffee_class": "Latte",
            "team_time": 3674.031,
            "lap_count": 1,
            "avg_speed": 36.74,
            "total_tss": 0,
            "total_if": 0,
            "total_np": 0,
            "team_name": "WKG GOAT HURDERS",
            "rider_count": 5,
            "completed": 0,
            "total_time_calc": 3674.031
        },
        {
            "riders": [
                {
                    "team_rank": 1,
                    "rider_rank": 4,
                    "rider_name": "Jason Smitherman (WTRL1)",
                    "rider_position": null,
                    "team_name": "WTRL",
                    "wkg": 3.6,
                    "power": 279,
                    "completed_laps": 1,
                    "total_time": 3550.589,
                    "time_gap": 0.404,
                    "avg_speed": 38.022,
                    "distance": 116962
                },
                {
                    "team_rank": 0,
                    "rider_rank": 2,
                    "rider_name": "Neil Ostenfeld &#128304;",
                    "rider_position": null,
                    "team_name": "Team Type 1",
                    "wkg": 4.6,
                    "power": 289,
                    "completed_laps": 1,
                    "total_time": 3550.397,
                    "time_gap": 0.212,
                    "avg_speed": 38.024,
                    "distance": 121681
                },
                {
                    "team_rank": 0,
                    "rider_rank": 5,
                    "rider_name": "Sean Casson(The BRaT Pack)",
                    "rider_position": null,
                    "team_name": "BRT",
                    "wkg": 4,
                    "power": 290,
                    "completed_laps": 1,
                    "total_time": 3591.637,
                    "time_gap": 41.452,
                    "avg_speed": 37.587,
                    "distance": 161615
                },
                {
                    "team_rank": 0,
                    "rider_rank": 1,
                    "rider_name": "Steve Milliken (WTRL)",
                    "rider_position": null,
                    "team_name": "WTRL",
                    "wkg": 4,
                    "power": 290,
                    "completed_laps": 1,
                    "total_time": 3550.185,
                    "time_gap": 0,
                    "avg_speed": 38.026,
                    "distance": 184248
                },
                {
                    "team_rank": 0,
                    "rider_rank": 3,
                    "rider_name": "Kim Lamb&aelig;k",
                    "rider_position": null,
                    "team_name": "Team Type 1",
                    "wkg": 3.9,
                    "power": 279,
                    "completed_laps": 1,
                    "total_time": 3550.578,
                    "time_gap": 0.393,
                    "avg_speed": 38.022,
                    "distance": 192800
                },
                {
                    "team_rank": 0,
                    "rider_rank": 6,
                    "rider_name": "Ryan Wilcox",
                    "rider_position": null,
                    "team_name": "Team Type 1",
                    "wkg": 3.5,
                    "power": 235,
                    "completed_laps": 1,
                    "total_time": 3697.002,
                    "time_gap": 146.817,
                    "avg_speed": 36.516,
                    "distance": 547199
                }
            ],
            "rank": 7,
            "total_distance": 402.54,
            "total_power": 3550.589,
            "zone": 2,
            "dropped_riders": 1,
            "coffee_class": "Espresso",
            "team_time": 3550.589,
            "lap_count": 1,
            "avg_speed": 38.02,
            "total_tss": 0,
            "total_if": 0,
            "total_np": 0,
            "team_name": "WTRL Pioneers",
            "rider_count": 6,
            "completed": 0,
            "total_time_calc": 3550.589
        },
        {
            "riders": [
                {
                    "team_rank": 0,
                    "rider_rank": 1,
                    "rider_name": "GORDON JACKSON ( WKG VOMIT )",
                    "rider_position": null,
                    "team_name": "teamWKG",
                    "wkg": 3.3,
                    "power": 284,
                    "completed_laps": 1,
                    "total_time": 3566.379,
                    "time_gap": 0,
                    "avg_speed": 37.854,
                    "distance": 19671
                },
                {
                    "team_rank": 1,
                    "rider_rank": 2,
                    "rider_name": "John Bytheway (WKG Vomit)",
                    "rider_position": null,
                    "team_name": "teamWKG",
                    "wkg": 3.6,
                    "power": 227,
                    "completed_laps": 1,
                    "total_time": 3566.398,
                    "time_gap": 0.019,
                    "avg_speed": 37.853,
                    "distance": 119215
                }
            ],
            "rank": 8,
            "total_distance": 418.349,
            "total_power": 3566.398,
            "zone": 2,
            "dropped_riders": 0,
            "coffee_class": "DNQ",
            "team_time": 3566.398,
            "lap_count": 1,
            "avg_speed": 37.85,
            "total_tss": 463,
            "total_if": 939,
            "total_np": 1393,
            "team_name": "WKG Torture",
            "rider_count": 2,
            "completed": 0,
            "total_time_calc": 3566.398
        },
        {
            "riders": [
                {
                    "team_rank": 0,
                    "rider_rank": 1,
                    "rider_name": "Ali Grant (Herd Armadillos)",
                    "rider_position": null,
                    "team_name": "",
                    "wkg": 2.5,
                    "power": 206,
                    "completed_laps": 1,
                    "total_time": 4259.267,
                    "time_gap": 0,
                    "avg_speed": 31.696,
                    "distance": 271488
                },
                {
                    "team_rank": 0,
                    "rider_rank": 2,
                    "rider_name": "Marius Midtskogen (Herd of Lions)",
                    "rider_position": null,
                    "team_name": "HERD",
                    "wkg": 2.6,
                    "power": 220,
                    "completed_laps": 1,
                    "total_time": 4259.538,
                    "time_gap": 0.271,
                    "avg_speed": 31.694,
                    "distance": 439203
                },
                {
                    "team_rank": 0,
                    "rider_rank": 4,
                    "rider_name": "Steve Jenks (Herd of Tigers)",
                    "rider_position": null,
                    "team_name": "HERD",
                    "wkg": 2.7,
                    "power": 176,
                    "completed_laps": 1,
                    "total_time": 4261.889,
                    "time_gap": 2.622,
                    "avg_speed": 31.676,
                    "distance": 585746
                },
                {
                    "team_rank": 1,
                    "rider_rank": 3,
                    "rider_name": "Lee Levy (Herd of Killer Bees)",
                    "rider_position": null,
                    "team_name": "HERD",
                    "wkg": 2.4,
                    "power": 182,
                    "completed_laps": 1,
                    "total_time": 4261.829,
                    "time_gap": 2.562,
                    "avg_speed": 31.677,
                    "distance": 837321
                }
            ],
            "rank": 17,
            "total_distance": 1113.78,
            "total_power": 4261.829,
            "zone": 2,
            "dropped_riders": 1,
            "coffee_class": "Latte",
            "team_time": 4261.829,
            "lap_count": 1,
            "avg_speed": 31.68,
            "total_tss": 469,
            "total_if": 972,
            "total_np": 1450,
            "team_name": "HERD of Armadillos",
            "rider_count": 4,
            "completed": 0,
            "total_time_calc": 4261.829
        },
        {
            "riders": [
                {
                    "team_rank": 0,
                    "rider_rank": 1,
                    "rider_name": "Janice North (Herd of Coyotes)",
                    "rider_position": null,
                    "team_name": "HERD",
                    "wkg": 2.3,
                    "power": 149,
                    "completed_laps": 1,
                    "total_time": 3914.376,
                    "time_gap": 0,
                    "avg_speed": 34.488,
                    "distance": 387253
                },
                {
                    "team_rank": 1,
                    "rider_rank": 3,
                    "rider_name": "Mike Starr (HERD)",
                    "rider_position": null,
                    "team_name": "HERD",
                    "wkg": 2.7,
                    "power": 211,
                    "completed_laps": 1,
                    "total_time": 3914.594,
                    "time_gap": 0.218,
                    "avg_speed": 34.486,
                    "distance": 949548
                },
                {
                    "team_rank": 0,
                    "rider_rank": 2,
                    "rider_name": "Scott Haller (Herd of Killer Bees)",
                    "rider_position": null,
                    "team_name": "HERD",
                    "wkg": 2.1,
                    "power": 216,
                    "completed_laps": 1,
                    "total_time": 3914.389,
                    "time_gap": 0.013,
                    "avg_speed": 34.488,
                    "distance": 1122925
                }
            ],
            "rank": 14,
            "total_distance": 766.545,
            "total_power": 3914.594,
            "zone": 3,
            "dropped_riders": 1,
            "coffee_class": "Mocha",
            "team_time": 3914.594,
            "lap_count": 1,
            "avg_speed": 34.49,
            "total_tss": 658,
            "total_if": 1281,
            "total_np": 1995,
            "team_name": "HERD of Killer Bees",
            "rider_count": 3,
            "completed": 0,
            "total_time_calc": 3914.594
        },
        {
            "riders": [
                {
                    "team_rank": 0,
                    "rider_rank": 2,
                    "rider_name": "H-G Becker (VZT) &#128062;",
                    "rider_position": null,
                    "team_name": " VEGAN ",
                    "wkg": 4,
                    "power": 269,
                    "completed_laps": 1,
                    "total_time": 3333.784,
                    "time_gap": 1.148,
                    "avg_speed": 40.495,
                    "distance": 1765
                },
                {
                    "team_rank": 0,
                    "rider_rank": 6,
                    "rider_name": "Stu Gardiner &#9445; (VZT)",
                    "rider_position": null,
                    "team_name": " VEGAN ",
                    "wkg": 3.5,
                    "power": 262,
                    "completed_laps": 1,
                    "total_time": 3334.109,
                    "time_gap": 1.473,
                    "avg_speed": 40.491,
                    "distance": 446939
                },
                {
                    "team_rank": 0,
                    "rider_rank": 3,
                    "rider_name": "Joakim Bergros (Vegan)",
                    "rider_position": null,
                    "team_name": " VEGAN ",
                    "wkg": 2.9,
                    "power": 269,
                    "completed_laps": 1,
                    "total_time": 3333.859,
                    "time_gap": 1.223,
                    "avg_speed": 40.494,
                    "distance": 584929
                },
                {
                    "team_rank": 1,
                    "rider_rank": 4,
                    "rider_name": "Jason Masterman &#9419; (VZT)",
                    "rider_position": null,
                    "team_name": " VEGAN ",
                    "wkg": 3.5,
                    "power": 225,
                    "completed_laps": 1,
                    "total_time": 3333.884,
                    "time_gap": 1.248,
                    "avg_speed": 40.493,
                    "distance": 759061
                },
                {
                    "team_rank": 0,
                    "rider_rank": 1,
                    "rider_name": "Marc Pierschel (VZT)",
                    "rider_position": null,
                    "team_name": " VEGAN ",
                    "wkg": 4.2,
                    "power": 258,
                    "completed_laps": 1,
                    "total_time": 3332.636,
                    "time_gap": 0,
                    "avg_speed": 40.508,
                    "distance": 918949
                },
                {
                    "team_rank": 0,
                    "rider_rank": 5,
                    "rider_name": "Zico Torre &#9419; (VZT)",
                    "rider_position": null,
                    "team_name": " VEGAN ",
                    "wkg": 3.5,
                    "power": 227,
                    "completed_laps": 1,
                    "total_time": 3333.96,
                    "time_gap": 1.324,
                    "avg_speed": 40.492,
                    "distance": 1001637
                }
            ],
            "rank": 2,
            "total_distance": 185.835,
            "total_power": 3333.884,
            "zone": 2,
            "dropped_riders": 1,
            "coffee_class": "Espresso",
            "team_time": 3333.884,
            "lap_count": 1,
            "avg_speed": 40.49,
            "total_tss": 462,
            "total_if": 949,
            "total_np": 1408,
            "team_name": "Vegan Vipers",
            "rider_count": 6,
            "completed": 0,
            "total_time_calc": 3333.884
        },
        {
            "riders": [
                {
                    "team_rank": 1,
                    "rider_rank": 4,
                    "rider_name": "Miguel Rola Costa (TugaZRT Cimbalino)",
                    "rider_position": null,
                    "team_name": "TugaZRT",
                    "wkg": 3.5,
                    "power": 264,
                    "completed_laps": 1,
                    "total_time": 3727.117,
                    "time_gap": 0.133,
                    "avg_speed": 36.221,
                    "distance": 94972
                },
                {
                    "team_rank": 0,
                    "rider_rank": 3,
                    "rider_name": "Jorge Caldeira &#128057;",
                    "rider_position": null,
                    "team_name": "TugaZRT",
                    "wkg": 3.2,
                    "power": 228,
                    "completed_laps": 1,
                    "total_time": 3727.087,
                    "time_gap": 0.103,
                    "avg_speed": 36.221,
                    "distance": 181509
                },
                {
                    "team_rank": 0,
                    "rider_rank": 1,
                    "rider_name": "Rui In&aacute;cio",
                    "rider_position": null,
                    "team_name": "TugaZRT",
                    "wkg": 3.2,
                    "power": 217,
                    "completed_laps": 1,
                    "total_time": 3726.984,
                    "time_gap": 0,
                    "avg_speed": 36.222,
                    "distance": 196516
                },
                {
                    "team_rank": 0,
                    "rider_rank": 2,
                    "rider_name": "Antonio Gouveia (TugaZRT Cimbalino)",
                    "rider_position": null,
                    "team_name": "TugaZRT",
                    "wkg": 2.9,
                    "power": 241,
                    "completed_laps": 1,
                    "total_time": 3726.997,
                    "time_gap": 0.013,
                    "avg_speed": 36.222,
                    "distance": 680896
                },
                {
                    "team_rank": 0,
                    "rider_rank": 5,
                    "rider_name": "Jorge Dias (TugaZRT Cimbalino)",
                    "rider_position": null,
                    "team_name": "TugaZRT",
                    "wkg": 2.3,
                    "power": 163,
                    "completed_laps": 1,
                    "total_time": 4342.489,
                    "time_gap": 615.505,
                    "avg_speed": 31.088,
                    "distance": 1091952
                }
            ],
            "rank": 13,
            "total_distance": 579.068,
            "total_power": 3727.117,
            "zone": 2,
            "dropped_riders": 1,
            "coffee_class": "Latte",
            "team_time": 3727.117,
            "lap_count": 1,
            "avg_speed": 36.22,
            "total_tss": 0,
            "total_if": 0,
            "total_np": 0,
            "team_name": "TugaZ Cimbalino",
            "rider_count": 5,
            "completed": 0,
            "total_time_calc": 3727.117
        },
        {
            "riders": [
                {
                    "team_rank": 0,
                    "rider_rank": 2,
                    "rider_name": "Kurt Pauwels [R3R]",
                    "rider_position": null,
                    "team_name": "Race3R",
                    "wkg": 4.3,
                    "power": 347,
                    "completed_laps": 1,
                    "total_time": 3147.045,
                    "time_gap": 0.029,
                    "avg_speed": 42.897,
                    "distance": 108458
                },
                {
                    "team_rank": 0,
                    "rider_rank": 7,
                    "rider_name": "P. Wolf Race3R@Wolfie B",
                    "rider_position": null,
                    "team_name": "Race3R",
                    "wkg": 2.9,
                    "power": 249,
                    "completed_laps": 1,
                    "total_time": 3681.611,
                    "time_gap": 534.595,
                    "avg_speed": 36.669,
                    "distance": 117273
                },
                {
                    "team_rank": 0,
                    "rider_rank": 1,
                    "rider_name": "Shane Wiseman (R3R Rebels)",
                    "rider_position": null,
                    "team_name": "Race3R",
                    "wkg": 3.9,
                    "power": 305,
                    "completed_laps": 1,
                    "total_time": 3147.016,
                    "time_gap": 0,
                    "avg_speed": 42.898,
                    "distance": 143100
                },
                {
                    "team_rank": 0,
                    "rider_rank": 6,
                    "rider_name": "David Shepherd (R3R Rebels)",
                    "rider_position": null,
                    "team_name": "Race3R",
                    "wkg": 3.7,
                    "power": 285,
                    "completed_laps": 1,
                    "total_time": 3157.802,
                    "time_gap": 10.786,
                    "avg_speed": 42.751,
                    "distance": 318806
                },
                {
                    "team_rank": 0,
                    "rider_rank": 5,
                    "rider_name": "Rich Noble (R3R Rebels)",
                    "rider_position": null,
                    "team_name": "Race3R",
                    "wkg": 3.7,
                    "power": 335,
                    "completed_laps": 1,
                    "total_time": 3148.185,
                    "time_gap": 1.169,
                    "avg_speed": 42.882,
                    "distance": 353573
                },
                {
                    "team_rank": 1,
                    "rider_rank": 4,
                    "rider_name": "ALESSIO LEO (R3R Rebels)",
                    "rider_position": null,
                    "team_name": "Race3R",
                    "wkg": 3.6,
                    "power": 310,
                    "completed_laps": 1,
                    "total_time": 3148.049,
                    "time_gap": 1.033,
                    "avg_speed": 42.884,
                    "distance": 462862
                },
                {
                    "team_rank": 0,
                    "rider_rank": 3,
                    "rider_name": "Damo Frenchy (R3R Rebels)",
                    "rider_position": null,
                    "team_name": "Race3R",
                    "wkg": 4.2,
                    "power": 314,
                    "completed_laps": 1,
                    "total_time": 3147.378,
                    "time_gap": 0.362,
                    "avg_speed": 42.893,
                    "distance": 811037
                }
            ],
            "rank": 1,
            "total_distance": 0,
            "total_power": 3148.049,
            "zone": 1,
            "dropped_riders": 1,
            "coffee_class": "Frappe",
            "team_time": 3148.049,
            "lap_count": 1,
            "avg_speed": 42.88,
            "total_tss": 0,
            "total_if": 0,
            "total_np": 0,
            "team_name": "R3R Rebels",
            "rider_count": 7,
            "completed": 0,
            "total_time_calc": 3148.049
        },
        {
            "riders": [
                {
                    "team_rank": 0,
                    "rider_rank": 4,
                    "rider_name": "J. Emiliano (TugaZRT Bica)",
                    "rider_position": null,
                    "team_name": "TugaZRT",
                    "wkg": 2.1,
                    "power": 181,
                    "completed_laps": 1,
                    "total_time": 3970.592,
                    "time_gap": 0.677,
                    "avg_speed": 34,
                    "distance": 273118
                },
                {
                    "team_rank": 0,
                    "rider_rank": 1,
                    "rider_name": "Miguele Barroco (TugaZRT Bica)",
                    "rider_position": null,
                    "team_name": "TugaZRT",
                    "wkg": 2.2,
                    "power": 181,
                    "completed_laps": 1,
                    "total_time": 3969.915,
                    "time_gap": 0,
                    "avg_speed": 34.006,
                    "distance": 282907
                },
                {
                    "team_rank": 1,
                    "rider_rank": 3,
                    "rider_name": "Paulo Monteiro",
                    "rider_position": null,
                    "team_name": "TugaZRT",
                    "wkg": 2.5,
                    "power": 177,
                    "completed_laps": 1,
                    "total_time": 3970.566,
                    "time_gap": 0.651,
                    "avg_speed": 34,
                    "distance": 631207
                },
                {
                    "team_rank": 0,
                    "rider_rank": 2,
                    "rider_name": "Miguel Rem&iacute;zio (TugaZRT Bica)",
                    "rider_position": null,
                    "team_name": "TugaZRT",
                    "wkg": 2.2,
                    "power": 189,
                    "completed_laps": 1,
                    "total_time": 3970.345,
                    "time_gap": 0.43,
                    "avg_speed": 34.002,
                    "distance": 1119738
                }
            ],
            "rank": 16,
            "total_distance": 822.517,
            "total_power": 3970.566,
            "zone": 2,
            "dropped_riders": 1,
            "coffee_class": "Mocha",
            "team_time": 3970.566,
            "lap_count": 1,
            "avg_speed": 34,
            "total_tss": 0,
            "total_if": 0,
            "total_np": 0,
            "team_name": "TugaZRT Bica",
            "rider_count": 4,
            "completed": 0,
            "total_time_calc": 3970.566
        },
        {
            "riders": [
                {
                    "team_rank": 0,
                    "rider_rank": 2,
                    "rider_name": "Ricardo Gama &#128163;",
                    "rider_position": null,
                    "team_name": "TugaZRT",
                    "wkg": 3.5,
                    "power": 247,
                    "completed_laps": 1,
                    "total_time": 3633.953,
                    "time_gap": 0.023,
                    "avg_speed": 37.15,
                    "distance": 108059
                },
                {
                    "team_rank": 0,
                    "rider_rank": 1,
                    "rider_name": "Nuno Coutinho (TugaZRT Carioca)",
                    "rider_position": null,
                    "team_name": "TugaZRT",
                    "wkg": 3.9,
                    "power": 287,
                    "completed_laps": 1,
                    "total_time": 3633.93,
                    "time_gap": 0,
                    "avg_speed": 37.15,
                    "distance": 238895
                },
                {
                    "team_rank": 1,
                    "rider_rank": 3,
                    "rider_name": "Pedro Correia",
                    "rider_position": null,
                    "team_name": "TugaZRT",
                    "wkg": 3.5,
                    "power": 239,
                    "completed_laps": 1,
                    "total_time": 3634.184,
                    "time_gap": 0.254,
                    "avg_speed": 37.147,
                    "distance": 718875
                }
            ],
            "rank": 10,
            "total_distance": 486.135,
            "total_power": 3634.184,
            "zone": 2,
            "dropped_riders": 1,
            "coffee_class": "Frappe",
            "team_time": 3634.184,
            "lap_count": 1,
            "avg_speed": 37.15,
            "total_tss": 0,
            "total_if": 0,
            "total_np": 0,
            "team_name": "TugaZ Carioca",
            "rider_count": 3,
            "completed": 0,
            "total_time_calc": 3634.184
        },
        {
            "riders": [
                {
                    "team_rank": 0,
                    "rider_rank": 5,
                    "rider_name": "Mark Ley (R3R Bucks Fizz)",
                    "rider_position": null,
                    "team_name": "Race3R",
                    "wkg": 3.4,
                    "power": 238,
                    "completed_laps": 1,
                    "total_time": 3596.922,
                    "time_gap": 2.192,
                    "avg_speed": 37.532,
                    "distance": 113389
                },
                {
                    "team_rank": 0,
                    "rider_rank": 3,
                    "rider_name": "Thomas Kawelke (R3R Backstreet Boys)",
                    "rider_position": null,
                    "team_name": "Race3R",
                    "wkg": 3,
                    "power": 246,
                    "completed_laps": 1,
                    "total_time": 3596.411,
                    "time_gap": 1.681,
                    "avg_speed": 37.537,
                    "distance": 171376
                },
                {
                    "team_rank": 0,
                    "rider_rank": 2,
                    "rider_name": "Uros Huzjak (R3R Backstreet Boys)",
                    "rider_position": null,
                    "team_name": "Race3R",
                    "wkg": 3.3,
                    "power": 247,
                    "completed_laps": 1,
                    "total_time": 3594.924,
                    "time_gap": 0.194,
                    "avg_speed": 37.553,
                    "distance": 175588
                },
                {
                    "team_rank": 1,
                    "rider_rank": 4,
                    "rider_name": "Antony Ribot (R3R Backstreet Boys)",
                    "rider_position": null,
                    "team_name": "Race3R",
                    "wkg": 3.3,
                    "power": 221,
                    "completed_laps": 1,
                    "total_time": 3596.501,
                    "time_gap": 1.771,
                    "avg_speed": 37.536,
                    "distance": 187677
                },
                {
                    "team_rank": 0,
                    "rider_rank": 1,
                    "rider_name": "Martin Carew",
                    "rider_position": null,
                    "team_name": "Race3R",
                    "wkg": 2.9,
                    "power": 279,
                    "completed_laps": 1,
                    "total_time": 3594.73,
                    "time_gap": 0,
                    "avg_speed": 37.555,
                    "distance": 839018
                }
            ],
            "rank": 9,
            "total_distance": 448.452,
            "total_power": 3596.501,
            "zone": 2,
            "dropped_riders": 1,
            "coffee_class": "Latte",
            "team_time": 3596.501,
            "lap_count": 1,
            "avg_speed": 37.54,
            "total_tss": 0,
            "total_if": 0,
            "total_np": 0,
            "team_name": "R3R Bucks Fizz",
            "rider_count": 5,
            "completed": 0,
            "total_time_calc": 3596.501
        },
        {
            "riders": [
                {
                    "team_rank": 1,
                    "rider_rank": 3,
                    "rider_name": "Vincent Jacquot",
                    "rider_position": null,
                    "team_name": "U.C.Chamoy",
                    "wkg": 3.5,
                    "power": 241,
                    "completed_laps": 1,
                    "total_time": 3539.799,
                    "time_gap": 0.155,
                    "avg_speed": 38.138,
                    "distance": 463765
                },
                {
                    "team_rank": 0,
                    "rider_rank": 4,
                    "rider_name": "Sebastien Voulders &#128001;",
                    "rider_position": null,
                    "team_name": "U.C.Chamoy",
                    "wkg": 3.6,
                    "power": 259,
                    "completed_laps": 1,
                    "total_time": 3539.904,
                    "time_gap": 0.26,
                    "avg_speed": 38.137,
                    "distance": 482453
                },
                {
                    "team_rank": 0,
                    "rider_rank": 1,
                    "rider_name": "Mathieu BONNET",
                    "rider_position": null,
                    "team_name": "U.C.Chamoy",
                    "wkg": 3.5,
                    "power": 265,
                    "completed_laps": 1,
                    "total_time": 3539.644,
                    "time_gap": 0,
                    "avg_speed": 38.139,
                    "distance": 591599
                },
                {
                    "team_rank": 0,
                    "rider_rank": 2,
                    "rider_name": "tom fav &#128049;",
                    "rider_position": null,
                    "team_name": "U.C.Chamoy",
                    "wkg": 3.5,
                    "power": 272,
                    "completed_laps": 1,
                    "total_time": 3539.746,
                    "time_gap": 0.102,
                    "avg_speed": 38.138,
                    "distance": 762149
                }
            ],
            "rank": 6,
            "total_distance": 391.75,
            "total_power": 3539.799,
            "zone": 2,
            "dropped_riders": 1,
            "coffee_class": "Frappe",
            "team_time": 3539.799,
            "lap_count": 1,
            "avg_speed": 38.14,
            "total_tss": 0,
            "total_if": 0,
            "total_np": 0,
            "team_name": "UC Chamoy",
            "rider_count": 4,
            "completed": 0,
            "total_time_calc": 3539.799
        }
    ],
    "success": true,
    "loggedin": true
}